CHANGELOG.md
MANIFEST.in
README.md
requirements.txt
setup.py
keras_radam/__init__.py
keras_radam/backend.py
keras_radam/optimizer_v2.py
keras_radam/optimizers.py
keras_radam/selection.py
keras_radam/training.py
tensorflow_radam.egg-info/PKG-INFO
tensorflow_radam.egg-info/SOURCES.txt
tensorflow_radam.egg-info/dependency_links.txt
tensorflow_radam.egg-info/requires.txt
tensorflow_radam.egg-info/top_level.txt
tests/__init__.py
tests/official.py
tests/test_optimizers.py
tests/test_similar.py